bamt_light/__init__.py
bamt_light/builders/__init__.py
bamt_light/builders/builders_base.py
bamt_light/builders/composite_builder.py
bamt_light/display/__init__.py
bamt_light/display/display.py
bamt_light/external/__init__.py
bamt_light/external/pyBN/__init__.py
bamt_light/external/pyBN/classes/__init__.py
bamt_light/external/pyBN/classes/_tests/__init__.py
bamt_light/external/pyBN/classes/_tests/test_bayesnet.py
bamt_light/external/pyBN/classes/bayesnet.py
bamt_light/external/pyBN/utils/__init__.py
bamt_light/external/pyBN/utils/_tests/__init__.py
bamt_light/external/pyBN/utils/_tests/test_independence_tests.py
bamt_light/external/pyBN/utils/_tests/test_markov_blanket.py
bamt_light/external/pyBN/utils/_tests/test_orient_edges.py
bamt_light/external/pyBN/utils/_tests/test_random_sample.py
bamt_light/external/pyBN/utils/class_equivalence.py
bamt_light/external/pyBN/utils/data.py
bamt_light/external/pyBN/utils/graph.py
bamt_light/external/pyBN/utils/independence_tests.py
bamt_light/external/pyitlib/DiscreteRandomVariableUtils.py
bamt_light/external/pyitlib/__init__.py
bamt_light/log.py
bamt_light/logging.conf
bamt_light/networks/__init__.py
bamt_light/networks/base.py
bamt_light/networks/big_brave_bn.py
bamt_light/networks/composite_bn.py
bamt_light/networks/continuous_bn.py
bamt_light/networks/discrete_bn.py
bamt_light/networks/hybrid_bn.py
bamt_light/nodes/__init__.py
bamt_light/nodes/base.py
bamt_light/nodes/composite_continuous_node.py
bamt_light/nodes/composite_discrete_node.py
bamt_light/nodes/conditional_gaussian_node.py
bamt_light/nodes/conditional_logit_node.py
bamt_light/nodes/conditional_mixture_gaussian_node.py
bamt_light/nodes/discrete_node.py
bamt_light/nodes/gaussian_node.py
bamt_light/nodes/logit_node.py
bamt_light/nodes/mixture_gaussian_node.py
bamt_light/nodes/schema.py
bamt_light/preprocessors.py
bamt_light/utils/GraphUtils.py
bamt_light/utils/MathUtils.py
bamt_light/utils/__init__.py
bamt_light/utils/check_utils.py
bamt_light-0.0.3.dist-info/METADATA
bamt_light-0.0.3.dist-info/WHEEL
bamt_light-0.0.3.dist-info/RECORD
